[
    {
        "index": "001",
        "name": "小笃儿",
        "name_jp": "ツツケラ",
        "name_en": "Pikipek",
        "generation": "第七世代",
        "types": [
            "一般",
            "飞行"
        ],
        "meta": {
            "filter": "",
            "icon_position": "-1848px -1512px"
        },
        "national_index": "010"
    },
    {
        "index": "002",
        "name": "喇叭啄鸟",
        "name_jp": "ケララッパ",
        "name_en": "Trumbeak",
        "generation": "第七世代",
        "types": [
            "一般",
            "飞行"
        ],
        "meta": {
            "filter": "",
            "icon_position": "-1904px -1512px"
        },
        "national_index": "011"
    },
    {
        "index": "003",
        "name": "铳嘴大鸟",
        "name_jp": "ドデカバシ",
        "name_en": "Toucannon",
        "generation": "第七世代",
        "types": [
            "一般",
            "飞行"
        ],
        "meta": {
            "filter": "",
            "icon_position": "-1960px -1512px"
        },
        "national_index": "012"
    },
    {
        "index": "004",
        "name": "猫鼬少",
        "name_jp": "ヤングース",
        "name_en": "Yungoos",
        "generation": "第七世代",
        "types": [
            "一般"
        ],
        "meta": {
            "filter": "",
            "icon_position": "-2016px -1512px"
        },
        "national_index": "013"
    },
    {
        "index": "005",
        "name": "猫鼬探长",
        "name_jp": "デカグース",
        "name_en": "Gumshoos",
        "generation": "第七世代",
        "types": [
            "一般"
        ],
        "meta": {
            "filter": "",
            "icon_position": "-2072px -1512px"
        },
        "national_index": "014"
    },
    {
        "index": "006",
        "name": "小拉达-阿罗拉的样子",
        "name_jp": "コラッタ",
        "name_en": "Rattata",
        "generation": "第一世代",
        "types": [
            "恶",
            "一般"
        ],
        "meta": {
            "filter": "地",
            "icon_position": "-1960px 0px"
        },
        "national_index": "015"
    },
    {
        "index": "007",
        "name": "拉达-阿罗拉的样子",
        "name_jp": "ラッタ",
        "name_en": "Raticate",
        "generation": "第一世代",
        "types": [
            "恶",
            "一般"
        ],
        "meta": {
            "filter": "地",
            "icon_position": "-2128px 0px"
        },
        "national_index": "016"
    },
    {
        "index": "008",
        "name": "绿毛虫",
        "name_jp": "キャタピー",
        "name_en": "Caterpie",
        "generation": "第一世代",
        "types": [
            "虫"
        ],
        "meta": {
            "filter": "",
            "icon_position": "-1120px 0px"
        },
        "national_index": "017"
    },
    {
        "index": "009",
        "name": "铁甲蛹",
        "name_jp": "トランセル",
        "name_en": "Metapod",
        "generation": "第一世代",
        "types": [
            "虫"
        ],
        "meta": {
            "filter": "",
            "icon_position": "-1176px 0px"
        },
        "national_index": "018"
    },
    {
        "index": "010",
        "name": "巴大蝶",
        "name_jp": "バタフリー",
        "name_en": "Butterfree",
        "generation": "第一世代",
        "types": [
            "虫",
            "飞行"
        ],
        "meta": {
            "filter": "极",
            "icon_position": "-1232px 0px"
        },
        "national_index": "019"
    },
    {
        "index": "011",
        "name": "强颚鸡母虫",
        "name_jp": "アゴジムシ",
        "name_en": "Grubbin",
        "generation": "第七世代",
        "types": [
            "虫"
        ],
        "meta": {
            "filter": "",
            "icon_position": "-2128px -1512px"
        },
        "national_index": "034"
    },
    {
        "index": "012",
        "name": "虫电宝",
        "name_jp": "デンヂムシ",
        "name_en": "Charjabug",
        "generation": "第七世代",
        "types": [
            "虫",
            "电"
        ],
        "meta": {
            "filter": "",
            "icon_position": "-2184px -1512px"
        },
        "national_index": "035"
    },
    {
        "index": "013",
        "name": "锹农炮虫",
        "name_jp": "クワガノン",
        "name_en": "Vikavolt",
        "generation": "第七世代",
        "types": [
            "虫",
            "电"
        ],
        "meta": {
            "filter": "",
            "icon_position": "0px -1568px"
        },
        "national_index": "036"
    },
    {
        "index": "014",
        "name": "盆才怪",
        "name_jp": "ウソハチ",
        "name_en": "Bonsly",
        "generation": "第四世代",
        "types": [
            "岩石"
        ],
        "meta": {
            "filter": "",
            "icon_position": "-2128px -896px"
        },
        "national_index": "037"
    },
    {
        "index": "015",
        "name": "树才怪",
        "name_jp": "ウソッキー",
        "name_en": "Sudowoodo",
        "generation": "第二世代",
        "types": [
            "岩石"
        ],
        "meta": {
            "filter": "",
            "icon_position": "-1008px -392px"
        },
        "national_index": "038"
    },
    {
        "index": "016",
        "name": "小福蛋",
        "name_jp": "ピンプク",
        "name_en": "Happiny",
        "generation": "第四世代",
        "types": [
            "一般"
        ],
        "meta": {
            "filter": "",
            "icon_position": "0px -952px"
        },
        "national_index": "039"
    },
    {
        "index": "017",
        "name": "吉利蛋",
        "name_jp": "ラッキー",
        "name_en": "Chansey",
        "generation": "第一世代",
        "types": [
            "一般"
        ],
        "meta": {
            "filter": "",
            "icon_position": "-2016px -224px"
        },
        "national_index": "040"
    },
    {
        "index": "018",
        "name": "幸福蛋",
        "name_jp": "ハピナス",
        "name_en": "Blissey",
        "generation": "第二世代",
        "types": [
            "一般"
        ],
        "meta": {
            "filter": "",
            "icon_position": "-560px -560px"
        },
        "national_index": "041"
    },
    {
        "index": "019",
        "name": "长翅鸥",
        "name_jp": "キャモメ",
        "name_en": "Wingull",
        "generation": "第三世代",
        "types": [
            "水",
            "飞行"
        ],
        "meta": {
            "filter": "",
            "icon_position": "-1064px -616px"
        },
        "national_index": "047"
    },
    {
        "index": "020",
        "name": "大嘴鸥",
        "name_jp": "ペリッパー",
        "name_en": "Pelipper",
        "generation": "第三世代",
        "types": [
            "水",
            "飞行"
        ],
        "meta": {
            "filter": "",
            "icon_position": "-1120px -616px"
        },
        "national_index": "048"
    },
    {
        "index": "021",
        "name": "好胜蟹",
        "name_jp": "マケンカニ",
        "name_en": "Crabrawler",
        "generation": "第七世代",
        "types": [
            "格斗"
        ],
        "meta": {
            "filter": "",
            "icon_position": "-56px -1568px"
        },
        "national_index": "071"
    },
    {
        "index": "022",
        "name": "好胜毛蟹",
        "name_jp": "ケケンカニ",
        "name_en": "Crabominable",
        "generation": "第七世代",
        "types": [
            "格斗",
            "冰"
        ],
        "meta": {
            "filter": "",
            "icon_position": "-112px -1568px"
        },
        "national_index": "072"
    },
    {
        "index": "023",
        "name": "鬼斯",
        "name_jp": "ゴース",
        "name_en": "Gastly",
        "generation": "第一世代",
        "types": [
            "幽灵",
            "毒"
        ],
        "meta": {
            "filter": "",
            "icon_position": "-168px -224px"
        },
        "national_index": "073"
    },
    {
        "index": "024",
        "name": "鬼斯通",
        "name_jp": "ゴースト",
        "name_en": "Haunter",
        "generation": "第一世代",
        "types": [
            "幽灵",
            "毒"
        ],
        "meta": {
            "filter": "",
            "icon_position": "-224px -224px"
        },
        "national_index": "074"
    },
    {
        "index": "025",
        "name": "耿鬼",
        "name_jp": "ゲンガー",
        "name_en": "Gengar",
        "generation": "第一世代",
        "types": [
            "幽灵",
            "毒"
        ],
        "meta": {
            "filter": "超:极",
            "icon_position": "-280px -224px"
        },
        "national_index": "075"
    },
    {
        "index": "026",
        "name": "超音蝠",
        "name_jp": "ズバット",
        "name_en": "Zubat",
        "generation": "第一世代",
        "types": [
            "毒",
            "飞行"
        ],
        "meta": {
            "filter": "",
            "icon_position": "-112px -112px"
        },
        "national_index": "080"
    },
    {
        "index": "027",
        "name": "大嘴蝠",
        "name_jp": "ゴルバット",
        "name_en": "Golbat",
        "generation": "第一世代",
        "types": [
            "毒",
            "飞行"
        ],
        "meta": {
            "filter": "",
            "icon_position": "-224px -112px"
        },
        "national_index": "081"
    },
    {
        "index": "028",
        "name": "叉字蝠",
        "name_jp": "クロバット",
        "name_en": "Crobat",
        "generation": "第二世代",
        "types": [
            "毒",
            "飞行"
        ],
        "meta": {
            "filter": "",
            "icon_position": "-2184px -336px"
        },
        "national_index": "082"
    },
    {
        "index": "029",
        "name": "地鼠-阿罗拉的样子",
        "name_jp": "ディグダ",
        "name_en": "Diglett",
        "generation": "第一世代",
        "types": [
            "地面",
            "钢"
        ],
        "meta": {
            "filter": "地",
            "icon_position": "-896px -112px"
        },
        "national_index": "085"
    },
    {
        "index": "030",
        "name": "三地鼠-阿罗拉的样子",
        "name_jp": "ダグトリオ",
        "name_en": "Dugtrio",
        "generation": "第一世代",
        "types": [
            "地面",
            "钢"
        ],
        "meta": {
            "filter": "地",
            "icon_position": "-1008px -112px"
        },
        "national_index": "086"
    },
    {
        "index": "031",
        "name": "花舞鸟-呼拉呼拉风格",
        "name_jp": "オドリドリ",
        "name_en": "Oricorio",
        "generation": "第七世代",
        "types": [
            "超能力",
            "飞行"
        ],
        "meta": {
            "filter": "",
            "icon_position": "-280px -1568px"
        },
        "national_index": "097"
    },
    {
        "index": "032",
        "name": "可达鸭",
        "name_jp": "コダック",
        "name_en": "Psyduck",
        "generation": "第一世代",
        "types": [
            "水"
        ],
        "meta": {
            "filter": "",
            "icon_position": "-1400px -112px"
        },
        "national_index": "107"
    },
    {
        "index": "033",
        "name": "哥达鸭",
        "name_jp": "ゴルダック",
        "name_en": "Golduck",
        "generation": "第一世代",
        "types": [
            "水"
        ],
        "meta": {
            "filter": "",
            "icon_position": "-1456px -112px"
        },
        "national_index": "108"
    },
    {
        "index": "034",
        "name": "鲤鱼王",
        "name_jp": "コイキング",
        "name_en": "Magikarp",
        "generation": "第一世代",
        "types": [
            "水"
        ],
        "meta": {
            "filter": "",
            "icon_position": "-1176px -280px"
        },
        "national_index": "111"
    },
    {
        "index": "035",
        "name": "暴鲤龙",
        "name_jp": "ギャラドス",
        "name_en": "Gyarados",
        "generation": "第一世代",
        "types": [
            "水",
            "飞行"
        ],
        "meta": {
            "filter": "超",
            "icon_position": "-1288px -280px"
        },
        "national_index": "112"
    },
    {
        "index": "036",
        "name": "泥泥鳅",
        "name_jp": "ドジョッチ",
        "name_en": "Barboach",
        "generation": "第三世代",
        "types": [
            "水",
            "地面"
        ],
        "meta": {
            "filter": "",
            "icon_position": "-952px -728px"
        },
        "national_index": "113"
    },
    {
        "index": "037",
        "name": "鲶鱼王",
        "name_jp": "ナマズン",
        "name_en": "Whiscash",
        "generation": "第三世代",
        "types": [
            "水",
            "地面"
        ],
        "meta": {
            "filter": "",
            "icon_position": "-1008px -728px"
        },
        "national_index": "114"
    },
    {
        "index": "038",
        "name": "玛瑙水母",
        "name_jp": "メノクラゲ",
        "name_en": "Tentacool",
        "generation": "第一世代",
        "types": [
            "水",
            "毒"
        ],
        "meta": {
            "filter": "",
            "icon_position": "-560px -168px"
        },
        "national_index": "129"
    },
    {
        "index": "039",
        "name": "毒刺水母",
        "name_jp": "ドククラゲ",
        "name_en": "Tentacruel",
        "generation": "第一世代",
        "types": [
            "水",
            "毒"
        ],
        "meta": {
            "filter": "",
            "icon_position": "-616px -168px"
        },
        "national_index": "130"
    },
    {
        "index": "040",
        "name": "荧光鱼",
        "name_jp": "ケイコウオ",
        "name_en": "Finneon",
        "generation": "第四世代",
        "types": [
            "水"
        ],
        "meta": {
            "filter": "",
            "icon_position": "-1400px -952px"
        },
        "national_index": "131"
    },
    {
        "index": "041",
        "name": "霓虹鱼",
        "name_jp": "ネオラント",
        "name_en": "Lumineon",
        "generation": "第四世代",
        "types": [
            "水"
        ],
        "meta": {
            "filter": "",
            "icon_position": "-1512px -952px"
        },
        "national_index": "132"
    },
    {
        "index": "042",
        "name": "弱丁鱼",
        "name_jp": "ヨワシ",
        "name_en": "Wishiwashi",
        "generation": "第七世代",
        "types": [
            "水"
        ],
        "meta": {
            "filter": "",
            "icon_position": "-728px -1568px"
        },
        "national_index": "133"
    },
    {
        "index": "043",
        "name": "爱心鱼",
        "name_jp": "ラブカス",
        "name_en": "Luvdisc",
        "generation": "第三世代",
        "types": [
            "水"
        ],
        "meta": {
            "filter": "",
            "icon_position": "-896px -784px"
        },
        "national_index": "134"
    },
    {
        "index": "044",
        "name": "太阳珊瑚",
        "name_jp": "サニーゴ",
        "name_en": "Corsola",
        "generation": "第二世代",
        "types": [
            "水",
            "岩石"
        ],
        "meta": {
            "filter": "地",
            "icon_position": "-1400px -504px"
        },
        "national_index": "135"
    },
    {
        "index": "045",
        "name": "好坏星",
        "name_jp": "ヒドイデ",
        "name_en": "Mareanie",
        "generation": "第七世代",
        "types": [
            "毒",
            "水"
        ],
        "meta": {
            "filter": "",
            "icon_position": "-840px -1568px"
        },
        "national_index": "136"
    },
    {
        "index": "046",
        "name": "超坏星",
        "name_jp": "ドヒドイデ",
        "name_en": "Toxapex",
        "generation": "第七世代",
        "types": [
            "毒",
            "水"
        ],
        "meta": {
            "filter": "",
            "icon_position": "-896px -1568px"
        },
        "national_index": "137"
    },
    {
        "index": "047",
        "name": "铁炮鱼",
        "name_jp": "テッポウオ",
        "name_en": "Remoraid",
        "generation": "第二世代",
        "types": [
            "水"
        ],
        "meta": {
            "filter": "",
            "icon_position": "-1512px -504px"
        },
        "national_index": "143"
    },
    {
        "index": "048",
        "name": "章鱼桶",
        "name_jp": "オクタン",
        "name_en": "Octillery",
        "generation": "第二世代",
        "types": [
            "水"
        ],
        "meta": {
            "filter": "",
            "icon_position": "-1568px -504px"
        },
        "national_index": "144"
    },
    {
        "index": "049",
        "name": "小球飞鱼",
        "name_jp": "タマンタ",
        "name_en": "Mantyke",
        "generation": "第四世代",
        "types": [
            "水",
            "飞行"
        ],
        "meta": {
            "filter": "",
            "icon_position": "-1624px -952px"
        },
        "national_index": "145"
    },
    {
        "index": "050",
        "name": "巨翅飞鱼",
        "name_jp": "マンタイン",
        "name_en": "Mantine",
        "generation": "第二世代",
        "types": [
            "水",
            "飞行"
        ],
        "meta": {
            "filter": "",
            "icon_position": "-1736px -504px"
        },
        "national_index": "146"
    },
    {
        "index": "051",
        "name": "小约克",
        "name_jp": "ヨーテリー",
        "name_en": "Lillipup",
        "generation": "第五世代",
        "types": [
            "一般"
        ],
        "meta": {
            "filter": "",
            "icon_position": "-1792px -1064px"
        },
        "national_index": "0506"
    },
    {
        "index": "052",
        "name": "哈约克",
        "name_jp": "ハーデリア",
        "name_en": "Herdier",
        "generation": "第五世代",
        "types": [
            "一般"
        ],
        "meta": {
            "filter": "",
            "icon_position": "-1848px -1064px"
        },
        "national_index": "0507"
    },
    {
        "index": "053",
        "name": "长毛狗",
        "name_jp": "ムーランド",
        "name_en": "Stoutland",
        "generation": "第五世代",
        "types": [
            "一般"
        ],
        "meta": {
            "filter": "",
            "icon_position": "-1904px -1064px"
        },
        "national_index": "0508"
    },
    {
        "index": "054",
        "name": "伊布",
        "name_jp": "イーブイ",
        "name_en": "Eevee",
        "generation": "第一世代",
        "types": [
            "一般"
        ],
        "meta": {
            "filter": "Z:极:初",
            "icon_position": "-1624px -280px"
        },
        "national_index": "0133"
    },
    {
        "index": "055",
        "name": "水伊布",
        "name_jp": "シャワーズ",
        "name_en": "Vaporeon",
        "generation": "第一世代",
        "types": [
            "水"
        ],
        "meta": {
            "filter": "",
            "icon_position": "-1848px -280px"
        },
        "national_index": "0134"
    },
    {
        "index": "056",
        "name": "雷伊布",
        "name_jp": "サンダース",
        "name_en": "Jolteon",
        "generation": "第一世代",
        "types": [
            "电"
        ],
        "meta": {
            "filter": "",
            "icon_position": "-1904px -280px"
        },
        "national_index": "0135"
    },
    {
        "index": "057",
        "name": "火伊布",
        "name_jp": "ブースター",
        "name_en": "Flareon",
        "generation": "第一世代",
        "types": [
            "火"
        ],
        "meta": {
            "filter": "",
            "icon_position": "-1960px -280px"
        },
        "national_index": "0136"
    },
    {
        "index": "058",
        "name": "太阳伊布",
        "name_jp": "エーフィ",
        "name_en": "Espeon",
        "generation": "第二世代",
        "types": [
            "超能力"
        ],
        "meta": {
            "filter": "",
            "icon_position": "-1960px -392px"
        },
        "national_index": "0196"
    },
    {
        "index": "059",
        "name": "月亮伊布",
        "name_jp": "ブラッキー",
        "name_en": "Umbreon",
        "generation": "第二世代",
        "types": [
            "恶"
        ],
        "meta": {
            "filter": "",
            "icon_position": "-2016px -392px"
        },
        "national_index": "0197"
    },
    {
        "index": "060",
        "name": "叶伊布",
        "name_jp": "リーフィア",
        "name_en": "Leafeon",
        "generation": "第四世代",
        "types": [
            "草"
        ],
        "meta": {
            "filter": "",
            "icon_position": "-392px -1008px"
        },
        "national_index": "0470"
    },
    {
        "index": "061",
        "name": "冰伊布",
        "name_jp": "グレイシア",
        "name_en": "Glaceon",
        "generation": "第四世代",
        "types": [
            "冰"
        ],
        "meta": {
            "filter": "",
            "icon_position": "-448px -1008px"
        },
        "national_index": "0471"
    },
    {
        "index": "062",
        "name": "仙子伊布",
        "name_jp": "ニンフィア",
        "name_en": "Sylveon",
        "generation": "第六世代",
        "types": [
            "妖精"
        ],
        "meta": {
            "filter": "",
            "icon_position": "-1456px -1456px"
        },
        "national_index": "0700"
    },
    {
        "index": "063",
        "name": "咩利羊",
        "name_jp": "メリープ",
        "name_en": "Mareep",
        "generation": "第二世代",
        "types": [
            "电"
        ],
        "meta": {
            "filter": "",
            "icon_position": "-616px -392px"
        },
        "national_index": "0179"
    },
    {
        "index": "064",
        "name": "茸茸羊",
        "name_jp": "モココ",
        "name_en": "Flaaffy",
        "generation": "第二世代",
        "types": [
            "电"
        ],
        "meta": {
            "filter": "",
            "icon_position": "-672px -392px"
        },
        "national_index": "0180"
    },
    {
        "index": "065",
        "name": "电龙",
        "name_jp": "デンリュウ",
        "name_en": "Ampharos",
        "generation": "第二世代",
        "types": [
            "电"
        ],
        "meta": {
            "filter": "超",
            "icon_position": "-728px -392px"
        },
        "national_index": "0181"
    },
    {
        "index": "066",
        "name": "泥驴仔",
        "name_jp": "ドロバンコ",
        "name_en": "Mudbray",
        "generation": "第七世代",
        "types": [
            "地面"
        ],
        "meta": {
            "filter": "",
            "icon_position": "-952px -1568px"
        },
        "national_index": "0749"
    },
    {
        "index": "067",
        "name": "重泥挽马",
        "name_jp": "バンバドロ",
        "name_en": "Mudsdale",
        "generation": "第七世代",
        "types": [
            "地面"
        ],
        "meta": {
            "filter": "",
            "icon_position": "-1008px -1568px"
        },
        "national_index": "0750"
    },
    {
        "index": "068",
        "name": "宝宝丁",
        "name_jp": "ププリン",
        "name_en": "Igglybuff",
        "generation": "第二世代",
        "types": [
            "一般",
            "妖精"
        ],
        "meta": {
            "filter": "",
            "icon_position": "-280px -392px"
        },
        "national_index": "0174"
    },
    {
        "index": "069",
        "name": "胖丁",
        "name_jp": "プリン",
        "name_en": "Jigglypuff",
        "generation": "第一世代",
        "types": [
            "一般",
            "妖精"
        ],
        "meta": {
            "filter": "",
            "icon_position": "0px -112px"
        },
        "national_index": "0039"
    },
    {
        "index": "070",
        "name": "胖可丁",
        "name_jp": "プクリン",
        "name_en": "Wigglytuff",
        "generation": "第一世代",
        "types": [
            "一般",
            "妖精"
        ],
        "meta": {
            "filter": "",
            "icon_position": "-56px -112px"
        },
        "national_index": "0040"
    },
    {
        "index": "071",
        "name": "肯泰罗",
        "name_jp": "ケンタロス",
        "name_en": "Tauros",
        "generation": "第一世代",
        "types": [
            "一般"
        ],
        "meta": {
            "filter": "地",
            "icon_position": "-952px -280px"
        },
        "national_index": "0128"
    },
    {
        "index": "072",
        "name": "大奶罐",
        "name_jp": "ミルタンク",
        "name_en": "Miltank",
        "generation": "第二世代",
        "types": [
            "一般"
        ],
        "meta": {
            "filter": "",
            "icon_position": "-504px -560px"
        },
        "national_index": "0241"
    },
    {
        "index": "073",
        "name": "溜溜糖球",
        "name_jp": "アメタマ",
        "name_en": "Surskit",
        "generation": "第三世代",
        "types": [
            "虫",
            "水"
        ],
        "meta": {
            "filter": "",
            "icon_position": "-1400px -616px"
        },
        "national_index": "0283"
    },
    {
        "index": "074",
        "name": "雨翅蛾",
        "name_jp": "アメモース",
        "name_en": "Masquerain",
        "generation": "第三世代",
        "types": [
            "虫",
            "飞行"
        ],
        "meta": {
            "filter": "",
            "icon_position": "-1456px -616px"
        },
        "national_index": "0284"
    },
    {
        "index": "075",
        "name": "滴蛛",
        "name_jp": "シズクモ",
        "name_en": "Dewpider",
        "generation": "第七世代",
        "types": [
            "水",
            "虫"
        ],
        "meta": {
            "filter": "",
            "icon_position": "-1064px -1568px"
        },
        "national_index": "0751"
    },
    {
        "index": "076",
        "name": "滴蛛霸",
        "name_jp": "オニシズクモ",
        "name_en": "Araquanid",
        "generation": "第七世代",
        "types": [
            "水",
            "虫"
        ],
        "meta": {
            "filter": "",
            "icon_position": "-1120px -1568px"
        },
        "national_index": "0752"
    },
    {
        "index": "077",
        "name": "伪螳草",
        "name_jp": "カリキリ",
        "name_en": "Fomantis",
        "generation": "第七世代",
        "types": [
            "草"
        ],
        "meta": {
            "filter": "",
            "icon_position": "-1176px -1568px"
        },
        "national_index": "0753"
    },
    {
        "index": "078",
        "name": "兰螳花",
        "name_jp": "ラランテス",
        "name_en": "Lurantis",
        "generation": "第七世代",
        "types": [
            "草"
        ],
        "meta": {
            "filter": "",
            "icon_position": "-1232px -1568px"
        },
        "national_index": "0754"
    },
    {
        "index": "079",
        "name": "睡睡菇",
        "name_jp": "ネマシュ",
        "name_en": "Morelull",
        "generation": "第七世代",
        "types": [
            "草",
            "妖精"
        ],
        "meta": {
            "filter": "",
            "icon_position": "-1288px -1568px"
        },
        "national_index": "0755"
    },
    {
        "index": "080",
        "name": "灯罩夜菇",
        "name_jp": "マシェード",
        "name_en": "Shiinotic",
        "generation": "第七世代",
        "types": [
            "草",
            "妖精"
        ],
        "meta": {
            "filter": "",
            "icon_position": "-1344px -1568px"
        },
        "national_index": "0756"
    },
    {
        "index": "081",
        "name": "派拉斯",
        "name_jp": "パラス",
        "name_en": "Paras",
        "generation": "第一世代",
        "types": [
            "虫",
            "草"
        ],
        "meta": {
            "filter": "",
            "icon_position": "-616px -112px"
        },
        "national_index": "0046"
    },
    {
        "index": "082",
        "name": "派拉斯特",
        "name_jp": "パラセクト",
        "name_en": "Parasect",
        "generation": "第一世代",
        "types": [
            "虫",
            "草"
        ],
        "meta": {
            "filter": "",
            "icon_position": "-672px -112px"
        },
        "national_index": "0047"
    },
    {
        "index": "083",
        "name": "蚊香蝌蚪",
        "name_jp": "ニョロモ",
        "name_en": "Poliwag",
        "generation": "第一世代",
        "types": [
            "水"
        ],
        "meta": {
            "filter": "",
            "icon_position": "-1904px -112px"
        },
        "national_index": "0060"
    },
    {
        "index": "084",
        "name": "蚊香君",
        "name_jp": "ニョロゾ",
        "name_en": "Poliwhirl",
        "generation": "第一世代",
        "types": [
            "水"
        ],
        "meta": {
            "filter": "",
            "icon_position": "-1960px -112px"
        },
        "national_index": "0061"
    },
    {
        "index": "085",
        "name": "蚊香泳士",
        "name_jp": "ニョロボン",
        "name_en": "Poliwrath",
        "generation": "第一世代",
        "types": [
            "水",
            "格斗"
        ],
        "meta": {
            "filter": "",
            "icon_position": "-2016px -112px"
        },
        "national_index": "0062"
    },
    {
        "index": "086",
        "name": "蚊香蛙皇",
        "name_jp": "ニョロトノ",
        "name_en": "Politoed",
        "generation": "第二世代",
        "types": [
            "水"
        ],
        "meta": {
            "filter": "",
            "icon_position": "-1120px -392px"
        },
        "national_index": "0186"
    },
    {
        "index": "087",
        "name": "角金鱼",
        "name_jp": "トサキント",
        "name_en": "Goldeen",
        "generation": "第一世代",
        "types": [
            "水"
        ],
        "meta": {
            "filter": "",
            "icon_position": "-112px -280px"
        },
        "national_index": "0118"
    },
    {
        "index": "088",
        "name": "金鱼王",
        "name_jp": "アズマオウ",
        "name_en": "Seaking",
        "generation": "第一世代",
        "types": [
            "水"
        ],
        "meta": {
            "filter": "",
            "icon_position": "-224px -280px"
        },
        "national_index": "0119"
    },
    {
        "index": "089",
        "name": "野蛮鲈鱼",
        "name_jp": "バスラオ",
        "name_en": "Basculin",
        "generation": "第五世代",
        "types": [
            "水"
        ],
        "meta": {
            "filter": "",
            "icon_position": "0px -1176px"
        },
        "national_index": "0550"
    },
    {
        "index": "090",
        "name": "丑丑鱼",
        "name_jp": "ヒンバス",
        "name_en": "Feebas",
        "generation": "第三世代",
        "types": [
            "水"
        ],
        "meta": {
            "filter": "",
            "icon_position": "-1512px -728px"
        },
        "national_index": "0349"
    },
    {
        "index": "091",
        "name": "美纳斯",
        "name_jp": "ミロカロス",
        "name_en": "Milotic",
        "generation": "第三世代",
        "types": [
            "水"
        ],
        "meta": {
            "filter": "",
            "icon_position": "-1568px -728px"
        },
        "national_index": "0350"
    },
    {
        "index": "092",
        "name": "保姆曼波",
        "name_jp": "ママンボウ",
        "name_en": "Alomomola",
        "generation": "第五世代",
        "types": [
            "水"
        ],
        "meta": {
            "filter": "",
            "icon_position": "-1232px -1232px"
        },
        "national_index": "0594"
    },
    {
        "index": "093",
        "name": "小箭雀",
        "name_jp": "ヤヤコマ",
        "name_en": "Fletchling",
        "generation": "第六世代",
        "types": [
            "一般",
            "飞行"
        ],
        "meta": {
            "filter": "",
            "icon_position": "-1288px -1344px"
        },
        "national_index": "0661"
    },
    {
        "index": "094",
        "name": "火箭雀",
        "name_jp": "ヒノヤコマ",
        "name_en": "Fletchinder",
        "generation": "第六世代",
        "types": [
            "火",
            "飞行"
        ],
        "meta": {
            "filter": "",
            "icon_position": "-1344px -1344px"
        },
        "national_index": "0662"
    },
    {
        "index": "095",
        "name": "烈箭鹰",
        "name_jp": "ファイアロー",
        "name_en": "Talonflame",
        "generation": "第六世代",
        "types": [
            "火",
            "飞行"
        ],
        "meta": {
            "filter": "",
            "icon_position": "-1400px -1344px"
        },
        "national_index": "0663"
    },
    {
        "index": "096",
        "name": "夜盗火蜥",
        "name_jp": "ヤトウモリ",
        "name_en": "Salandit",
        "generation": "第七世代",
        "types": [
            "毒",
            "火"
        ],
        "meta": {
            "filter": "",
            "icon_position": "-1400px -1568px"
        },
        "national_index": "0757"
    },
    {
        "index": "097",
        "name": "焰后蜥",
        "name_jp": "エンニュート",
        "name_en": "Salazzle",
        "generation": "第七世代",
        "types": [
            "毒",
            "火"
        ],
        "meta": {
            "filter": "",
            "icon_position": "-1456px -1568px"
        },
        "national_index": "0758"
    },
    {
        "index": "098",
        "name": "卡拉卡拉",
        "name_jp": "カラカラ",
        "name_en": "Cubone",
        "generation": "第一世代",
        "types": [
            "地面"
        ],
        "meta": {
            "filter": "",
            "icon_position": "-1288px -224px"
        },
        "national_index": "0104"
    },
    {
        "index": "099",
        "name": "嘎啦嘎啦-阿罗拉的样子",
        "name_jp": "ガラガラ",
        "name_en": "Marowak",
        "generation": "第一世代",
        "types": [
            "火",
            "幽灵"
        ],
        "meta": {
            "filter": "地",
            "icon_position": "-1400px -224px"
        },
        "national_index": "0105"
    },
    {
        "index": "100",
        "name": "袋兽",
        "name_jp": "ガルーラ",
        "name_en": "Kangaskhan",
        "generation": "第一世代",
        "types": [
            "一般"
        ],
        "meta": {
            "filter": "超",
            "icon_position": "-2128px -224px"
        },
        "national_index": "0115"
    },
    {
        "index": "101",
        "name": "鸭嘴宝宝",
        "name_jp": "ブビィ",
        "name_en": "Magby",
        "generation": "第二世代",
        "types": [
            "火"
        ],
        "meta": {
            "filter": "",
            "icon_position": "-448px -560px"
        },
        "national_index": "0240"
    },
    {
        "index": "102",
        "name": "鸭嘴火兽",
        "name_jp": "ブーバー",
        "name_en": "Magmar",
        "generation": "第一世代",
        "types": [
            "火"
        ],
        "meta": {
            "filter": "",
            "icon_position": "-784px -280px"
        },
        "national_index": "0126"
    },
    {
        "index": "103",
        "name": "鸭嘴炎兽",
        "name_jp": "ブーバーン",
        "name_en": "Magmortar",
        "generation": "第四世代",
        "types": [
            "火"
        ],
        "meta": {
            "filter": "",
            "icon_position": "-224px -1008px"
        },
        "national_index": "0467"
    },
    {
        "index": "104",
        "name": "燃烧虫",
        "name_jp": "メラルバ",
        "name_en": "Larvesta",
        "generation": "第五世代",
        "types": [
            "虫",
            "火"
        ],
        "meta": {
            "filter": "",
            "icon_position": "-1456px -1288px"
        },
        "national_index": "0636"
    },
    {
        "index": "105",
        "name": "火神蛾",
        "name_jp": "ウルガモス",
        "name_en": "Volcarona",
        "generation": "第五世代",
        "types": [
            "虫",
            "火"
        ],
        "meta": {
            "filter": "",
            "icon_position": "-1512px -1288px"
        },
        "national_index": "0637"
    },
    {
        "index": "106",
        "name": "童偶熊",
        "name_jp": "ヌイコグマ",
        "name_en": "Stufful",
        "generation": "第七世代",
        "types": [
            "一般",
            "格斗"
        ],
        "meta": {
            "filter": "",
            "icon_position": "-1512px -1568px"
        },
        "national_index": "0759"
    },
    {
        "index": "107",
        "name": "穿着熊",
        "name_jp": "キテルグマ",
        "name_en": "Bewear",
        "generation": "第七世代",
        "types": [
            "一般",
            "格斗"
        ],
        "meta": {
            "filter": "",
            "icon_position": "-1568px -1568px"
        },
        "national_index": "0760"
    },
    {
        "index": "108",
        "name": "甜竹竹",
        "name_jp": "アマカジ",
        "name_en": "Bounsweet",
        "generation": "第七世代",
        "types": [
            "草"
        ],
        "meta": {
            "filter": "",
            "icon_position": "-1624px -1568px"
        },
        "national_index": "0761"
    },
    {
        "index": "109",
        "name": "甜舞妮",
        "name_jp": "アママイコ",
        "name_en": "Steenee",
        "generation": "第七世代",
        "types": [
            "草"
        ],
        "meta": {
            "filter": "",
            "icon_position": "-1680px -1568px"
        },
        "national_index": "0762"
    },
    {
        "index": "110",
        "name": "甜冷美后",
        "name_jp": "アマージョ",
        "name_en": "Tsareena",
        "generation": "第七世代",
        "types": [
            "草"
        ],
        "meta": {
            "filter": "",
            "icon_position": "-1736px -1568px"
        },
        "national_index": "0763"
    },
    {
        "index": "111",
        "name": "花疗环环",
        "name_jp": "キュワワー",
        "name_en": "Comfey",
        "generation": "第七世代",
        "types": [
            "妖精"
        ],
        "meta": {
            "filter": "",
            "icon_position": "-1792px -1568px"
        },
        "national_index": "0764"
    },
    {
        "index": "112",
        "name": "凯罗斯",
        "name_jp": "カイロス",
        "name_en": "Pinsir",
        "generation": "第一世代",
        "types": [
            "虫"
        ],
        "meta": {
            "filter": "超",
            "icon_position": "-840px -280px"
        },
        "national_index": "0127"
    },
    {
        "index": "113",
        "name": "咕咕",
        "name_jp": "ホーホー",
        "name_en": "Hoothoot",
        "generation": "第二世代",
        "types": [
            "一般",
            "飞行"
        ],
        "meta": {
            "filter": "",
            "icon_position": "-1736px -336px"
        },
        "national_index": "0163"
    },
    {
        "index": "114",
        "name": "猫头夜鹰",
        "name_jp": "ヨルノズク",
        "name_en": "Noctowl",
        "generation": "第二世代",
        "types": [
            "一般",
            "飞行"
        ],
        "meta": {
            "filter": "",
            "icon_position": "-1792px -336px"
        },
        "national_index": "0164"
    },
    {
        "index": "115",
        "name": "变隐龙",
        "name_jp": "カクレオン",
        "name_en": "Kecleon",
        "generation": "第三世代",
        "types": [
            "一般"
        ],
        "meta": {
            "filter": "",
            "icon_position": "-1904px -728px"
        },
        "national_index": "0352"
    },
    {
        "index": "116",
        "name": "智挥猩",
        "name_jp": "ヤレユータン",
        "name_en": "Oranguru",
        "generation": "第七世代",
        "types": [
            "一般",
            "超能力"
        ],
        "meta": {
            "filter": "",
            "icon_position": "-1848px -1568px"
        },
        "national_index": "0765"
    },
    {
        "index": "117",
        "name": "投掷猴",
        "name_jp": "ナゲツケサル",
        "name_en": "Passimian",
        "generation": "第七世代",
        "types": [
            "格斗"
        ],
        "meta": {
            "filter": "",
            "icon_position": "-1904px -1568px"
        },
        "national_index": "0766"
    },
    {
        "index": "118",
        "name": "黏黏宝",
        "name_jp": "ヌメラ",
        "name_en": "Goomy",
        "generation": "第六世代",
        "types": [
            "龙"
        ],
        "meta": {
            "filter": "",
            "icon_position": "-1680px -1456px"
        },
        "national_index": "0704"
    },
    {
        "index": "119",
        "name": "黏美儿",
        "name_jp": "ヌメイル",
        "name_en": "Sliggoo",
        "generation": "第六世代",
        "types": [
            "龙"
        ],
        "meta": {
            "filter": "地",
            "icon_position": "-1736px -1456px"
        },
        "national_index": "0705"
    },
    {
        "index": "120",
        "name": "黏美龙",
        "name_jp": "ヌメルゴン",
        "name_en": "Goodra",
        "generation": "第六世代",
        "types": [
            "龙"
        ],
        "meta": {
            "filter": "地:准",
            "icon_position": "-1848px -1456px"
        },
        "national_index": "0706"
    },
    {
        "index": "121",
        "name": "飘浮泡泡",
        "name_jp": "ポワルン",
        "name_en": "Castform",
        "generation": "第三世代",
        "types": [
            "一般"
        ],
        "meta": {
            "filter": "",
            "icon_position": "-1680px -728px"
        },
        "national_index": "0351"
    },
    {
        "index": "122",
        "name": "胆小虫",
        "name_jp": "コソクムシ",
        "name_en": "Wimpod",
        "generation": "第七世代",
        "types": [
            "虫",
            "水"
        ],
        "meta": {
            "filter": "",
            "icon_position": "-1960px -1568px"
        },
        "national_index": "0767"
    },
    {
        "index": "123",
        "name": "具甲武者",
        "name_jp": "グソクムシャ",
        "name_en": "Golisopod",
        "generation": "第七世代",
        "types": [
            "虫",
            "水"
        ],
        "meta": {
            "filter": "",
            "icon_position": "-2016px -1568px"
        },
        "national_index": "0768"
    },
    {
        "index": "124",
        "name": "海星星",
        "name_jp": "ヒトデマン",
        "name_en": "Staryu",
        "generation": "第一世代",
        "types": [
            "水"
        ],
        "meta": {
            "filter": "",
            "icon_position": "-336px -280px"
        },
        "national_index": "0120"
    },
    {
        "index": "125",
        "name": "宝石海星",
        "name_jp": "スターミー",
        "name_en": "Starmie",
        "generation": "第一世代",
        "types": [
            "水",
            "超能力"
        ],
        "meta": {
            "filter": "超",
            "icon_position": "-392px -280px"
        },
        "national_index": "0121"
    },
    {
        "index": "126",
        "name": "沙丘娃",
        "name_jp": "スナバァ",
        "name_en": "Sandygast",
        "generation": "第七世代",
        "types": [
            "幽灵",
            "地面"
        ],
        "meta": {
            "filter": "",
            "icon_position": "-2072px -1568px"
        },
        "national_index": "0769"
    },
    {
        "index": "127",
        "name": "噬沙堡爷",
        "name_jp": "シロデスナ",
        "name_en": "Palossand",
        "generation": "第七世代",
        "types": [
            "幽灵",
            "地面"
        ],
        "meta": {
            "filter": "",
            "icon_position": "-2128px -1568px"
        },
        "national_index": "0770"
    },
    {
        "index": "128",
        "name": "菊石兽",
        "name_jp": "オムナイト",
        "name_en": "Omanyte",
        "generation": "第一世代",
        "types": [
            "岩石",
            "水"
        ],
        "meta": {
            "filter": "石",
            "icon_position": "-2072px -280px"
        },
        "national_index": "0138"
    },
    {
        "index": "129",
        "name": "多刺菊石兽",
        "name_jp": "オムスター",
        "name_en": "Omastar",
        "generation": "第一世代",
        "types": [
            "岩石",
            "水"
        ],
        "meta": {
            "filter": "",
            "icon_position": "-2128px -280px"
        },
        "national_index": "0139"
    },
    {
        "index": "130",
        "name": "化石盔",
        "name_jp": "カブト",
        "name_en": "Kabuto",
        "generation": "第一世代",
        "types": [
            "岩石",
            "水"
        ],
        "meta": {
            "filter": "石",
            "icon_position": "-2184px -280px"
        },
        "national_index": "0140"
    },
    {
        "index": "131",
        "name": "镰刀盔",
        "name_jp": "カブトプス",
        "name_en": "Kabutops",
        "generation": "第一世代",
        "types": [
            "岩石",
            "水"
        ],
        "meta": {
            "filter": "",
            "icon_position": "0px -336px"
        },
        "national_index": "0141"
    },
    {
        "index": "132",
        "name": "触手百合",
        "name_jp": "リリーラ",
        "name_en": "Lileep",
        "generation": "第三世代",
        "types": [
            "岩石",
            "草"
        ],
        "meta": {
            "filter": "石",
            "icon_position": "-1288px -728px"
        },
        "national_index": "0345"
    },
    {
        "index": "133",
        "name": "摇篮百合",
        "name_jp": "ユレイドル",
        "name_en": "Cradily",
        "generation": "第三世代",
        "types": [
            "岩石",
            "草"
        ],
        "meta": {
            "filter": "",
            "icon_position": "-1344px -728px"
        },
        "national_index": "0346"
    },
    {
        "index": "134",
        "name": "太古羽虫",
        "name_jp": "アノプス",
        "name_en": "Anorith",
        "generation": "第三世代",
        "types": [
            "岩石",
            "虫"
        ],
        "meta": {
            "filter": "石",
            "icon_position": "-1400px -728px"
        },
        "national_index": "0347"
    },
    {
        "index": "135",
        "name": "太古盔甲",
        "name_jp": "アーマルド",
        "name_en": "Armaldo",
        "generation": "第三世代",
        "types": [
            "岩石",
            "虫"
        ],
        "meta": {
            "filter": "",
            "icon_position": "-1456px -728px"
        },
        "national_index": "0348"
    },
    {
        "index": "136",
        "name": "头盖龙",
        "name_jp": "ズガイドス",
        "name_en": "Cranidos",
        "generation": "第四世代",
        "types": [
            "岩石"
        ],
        "meta": {
            "filter": "石",
            "icon_position": "-1960px -840px"
        },
        "national_index": "0408"
    },
    {
        "index": "137",
        "name": "战槌龙",
        "name_jp": "ラムパルド",
        "name_en": "Rampardos",
        "generation": "第四世代",
        "types": [
            "岩石"
        ],
        "meta": {
            "filter": "",
            "icon_position": "-2016px -840px"
        },
        "national_index": "0409"
    },
    {
        "index": "138",
        "name": "盾甲龙",
        "name_jp": "タテトプス",
        "name_en": "Shieldon",
        "generation": "第四世代",
        "types": [
            "岩石",
            "钢"
        ],
        "meta": {
            "filter": "石",
            "icon_position": "-2072px -840px"
        },
        "national_index": "0410"
    },
    {
        "index": "139",
        "name": "护城龙",
        "name_jp": "トリデプス",
        "name_en": "Bastiodon",
        "generation": "第四世代",
        "types": [
            "岩石",
            "钢"
        ],
        "meta": {
            "filter": "",
            "icon_position": "-2128px -840px"
        },
        "national_index": "0411"
    },
    {
        "index": "140",
        "name": "始祖小鸟",
        "name_jp": "アーケン",
        "name_en": "Archen",
        "generation": "第五世代",
        "types": [
            "岩石",
            "飞行"
        ],
        "meta": {
            "filter": "石",
            "icon_position": "-1288px -1176px"
        },
        "national_index": "0566"
    },
    {
        "index": "141",
        "name": "始祖大鸟",
        "name_jp": "アーケオス",
        "name_en": "Archeops",
        "generation": "第五世代",
        "types": [
            "岩石",
            "飞行"
        ],
        "meta": {
            "filter": "",
            "icon_position": "-1344px -1176px"
        },
        "national_index": "0567"
    },
    {
        "index": "142",
        "name": "原盖海龟",
        "name_jp": "プロトーガ",
        "name_en": "Tirtouga",
        "generation": "第五世代",
        "types": [
            "水",
            "岩石"
        ],
        "meta": {
            "filter": "石",
            "icon_position": "-1176px -1176px"
        },
        "national_index": "0564"
    },
    {
        "index": "143",
        "name": "肋骨海龟",
        "name_jp": "アバゴーラ",
        "name_en": "Carracosta",
        "generation": "第五世代",
        "types": [
            "水",
            "岩石"
        ],
        "meta": {
            "filter": "",
            "icon_position": "-1232px -1176px"
        },
        "national_index": "0565"
    },
    {
        "index": "144",
        "name": "宝宝暴龙",
        "name_jp": "チゴラス",
        "name_en": "Tyrunt",
        "generation": "第六世代",
        "types": [
            "岩石",
            "龙"
        ],
        "meta": {
            "filter": "石",
            "icon_position": "-1232px -1456px"
        },
        "national_index": "0696"
    },
    {
        "index": "145",
        "name": "怪颚龙",
        "name_jp": "ガチゴラス",
        "name_en": "Tyrantrum",
        "generation": "第六世代",
        "types": [
            "岩石",
            "龙"
        ],
        "meta": {
            "filter": "",
            "icon_position": "-1288px -1456px"
        },
        "national_index": "0697"
    },
    {
        "index": "146",
        "name": "冰雪龙",
        "name_jp": "アマルス",
        "name_en": "Amaura",
        "generation": "第六世代",
        "types": [
            "岩石",
            "冰"
        ],
        "meta": {
            "filter": "石",
            "icon_position": "-1344px -1456px"
        },
        "national_index": "0698"
    },
    {
        "index": "147",
        "name": "冰雪巨龙",
        "name_jp": "アマルルガ",
        "name_en": "Aurorus",
        "generation": "第六世代",
        "types": [
            "岩石",
            "冰"
        ],
        "meta": {
            "filter": "",
            "icon_position": "-1400px -1456px"
        },
        "national_index": "0699"
    },
    {
        "index": "148",
        "name": "幼基拉斯",
        "name_jp": "ヨーギラス",
        "name_en": "Larvitar",
        "generation": "第二世代",
        "types": [
            "岩石",
            "地面"
        ],
        "meta": {
            "filter": "",
            "icon_position": "-784px -560px"
        },
        "national_index": "0246"
    },
    {
        "index": "149",
        "name": "沙基拉斯",
        "name_jp": "サナギラス",
        "name_en": "Pupitar",
        "generation": "第二世代",
        "types": [
            "岩石",
            "地面"
        ],
        "meta": {
            "filter": "",
            "icon_position": "-840px -560px"
        },
        "national_index": "0247"
    },
    {
        "index": "150",
        "name": "班基拉斯",
        "name_jp": "バンギラス",
        "name_en": "Tyranitar",
        "generation": "第二世代",
        "types": [
            "岩石",
            "恶"
        ],
        "meta": {
            "filter": "超:准",
            "icon_position": "-896px -560px"
        },
        "national_index": "0248"
    },
    {
        "index": "151",
        "name": "小木灵",
        "name_jp": "ボクレー",
        "name_en": "Phantump",
        "generation": "第六世代",
        "types": [
            "幽灵",
            "草"
        ],
        "meta": {
            "filter": "",
            "icon_position": "-2016px -1456px"
        },
        "national_index": "0708"
    },
    {
        "index": "152",
        "name": "朽木妖",
        "name_jp": "オーロット",
        "name_en": "Trevenant",
        "generation": "第六世代",
        "types": [
            "幽灵",
            "草"
        ],
        "meta": {
            "filter": "",
            "icon_position": "-2072px -1456px"
        },
        "national_index": "0709"
    },
    {
        "index": "153",
        "name": "天然雀",
        "name_jp": "ネイティ",
        "name_en": "Natu",
        "generation": "第二世代",
        "types": [
            "超能力",
            "飞行"
        ],
        "meta": {
            "filter": "",
            "icon_position": "-448px -392px"
        },
        "national_index": "0177"
    },
    {
        "index": "154",
        "name": "天然鸟",
        "name_jp": "ネイティオ",
        "name_en": "Xatu",
        "generation": "第二世代",
        "types": [
            "超能力",
            "飞行"
        ],
        "meta": {
            "filter": "",
            "icon_position": "-504px -392px"
        },
        "national_index": "0178"
    },
    {
        "index": "155",
        "name": "朝北鼻",
        "name_jp": "ノズパス",
        "name_en": "Nosepass",
        "generation": "第三世代",
        "types": [
            "岩石"
        ],
        "meta": {
            "filter": "",
            "icon_position": "-56px -672px"
        },
        "national_index": "0299"
    },
    {
        "index": "156",
        "name": "大朝北鼻",
        "name_jp": "ダイノーズ",
        "name_en": "Probopass",
        "generation": "第四世代",
        "types": [
            "岩石",
            "钢"
        ],
        "meta": {
            "filter": "",
            "icon_position": "-840px -1008px"
        },
        "national_index": "0476"
    },
    {
        "index": "157",
        "name": "拳海参",
        "name_jp": "ナマコブシ",
        "name_en": "Pyukumuku",
        "generation": "第七世代",
        "types": [
            "水"
        ],
        "meta": {
            "filter": "",
            "icon_position": "-2184px -1568px"
        },
        "national_index": "0771"
    },
    {
        "index": "158",
        "name": "灯笼鱼",
        "name_jp": "チョンチー",
        "name_en": "Chinchou",
        "generation": "第二世代",
        "types": [
            "水",
            "电"
        ],
        "meta": {
            "filter": "",
            "icon_position": "0px -392px"
        },
        "national_index": "0170"
    },
    {
        "index": "159",
        "name": "电灯怪",
        "name_jp": "ランターン",
        "name_en": "Lanturn",
        "generation": "第二世代",
        "types": [
            "水",
            "电"
        ],
        "meta": {
            "filter": "",
            "icon_position": "-56px -392px"
        },
        "national_index": "0171"
    },
    {
        "index": "160",
        "name": "卡璞・蝶蝶",
        "name_jp": "カプ・テテフ",
        "name_en": "Tapu Lele",
        "generation": "第七世代",
        "types": [
            "超能力",
            "妖精"
        ],
        "meta": {
            "filter": "Z:传",
            "icon_position": "-2184px -1624px"
        },
        "national_index": "0786"
    }
]